data_dag/__init__.py
data_dag/dag_factory.py
data_dag/operator_factory/__init__.py
data_dag/operator_factory/base.py
data_dag/operator_factory/dynamic.py
data_dag/operator_factory/simple.py
data_dag-1.0.0.dist-info/WHEEL
data_dag-1.0.0.dist-info/METADATA
data_dag-1.0.0.dist-info/RECORD
