Metadata-Version: 2.1
Name: data-dag
Version: 1.0.0
Summary: Tooling to help build data-driven DAGs
Author-email: Rearc Data <data@rearc.io>
Requires-Python: >=3.8
Classifier: Programming Language :: Python :: 3
Classifier: License :: OSI Approved :: MIT License
Classifier: Operating System :: OS Independent
Requires-Dist: apache-airflow>=2.6.3
Requires-Dist: typing_extensions>=4
Requires-Dist: pydantic==2.*
Project-URL: Bug Tracker, https://github.com/rearc-data/data-dag/issues
Project-URL: Homepage, https://github.com/rearc-data/data-dag
